hek_pool/CHANGELOG.MD
hek_pool/LICENSE.TXT
hek_pool/README.txt
hek_pool/__init__.py
hek_pool/__main__.py
hek_pool/app_window.py
hek_pool/config_def.py
hek_pool/constants.py
hek_pool/help_text.py
hek_pool/msg.dat
hek_pool/ogg_v1.1.2_dll_fix.zip
hek_pool/pool.ico
hek_pool/pool.png
hek_pool/pool_help.txt
hek_pool/run.py
hek_pool/util.py
hek_pool/cmd_lists/all_maps.txt
"hek_pool/cmd_lists/compile bsp, lightmaps, and build map.txt"
hek_pool/cmd_lists/compile object.txt
hek_pool-1.5.0.dist-info/LICENSE.TXT
hek_pool-1.5.0.dist-info/METADATA
hek_pool-1.5.0.dist-info/WHEEL
hek_pool-1.5.0.dist-info/top_level.txt
hek_pool-1.5.0.dist-info/RECORD
