Metadata-Version: 2.1
Name: hek-pool
Version: 1.5.0
Summary: UNKNOWN
Home-page: https://github.com/Sigmmma/hek_pool
Author: Devin Bobadilla, Michelle van der Graaf
Author-email: MoeMakesStuff@gmail.com
License: MIT
Platform: POSIX
Platform: Windows
Classifier: Development Status :: 4 - Beta
Classifier: Intended Audience :: End Users/Desktop
Classifier: License :: OSI Approved :: MIT License
Classifier: Programming Language :: Python
Classifier: Programming Language :: Python :: 3
Classifier: Programming Language :: Python :: 3.5
Classifier: Programming Language :: Python :: 3.6
Classifier: Programming Language :: Python :: 3.7
Classifier: Programming Language :: Python :: 3.8
Classifier: Programming Language :: Python :: 3 :: Only
Requires: supyr_struct
Requires: threadsafe_tkinter
Requires: mozzarilla
Provides: hek_pool
Requires-Dist: supyr-struct
Requires-Dist: threadsafe-tkinter
Requires-Dist: mozzarilla
